reflex_giscus/__init__.py
reflex_giscus/giscus.py
reflex_giscus-0.1.0.dist-info/LICENSE
reflex_giscus-0.1.0.dist-info/METADATA
reflex_giscus-0.1.0.dist-info/WHEEL
reflex_giscus-0.1.0.dist-info/top_level.txt
reflex_giscus-0.1.0.dist-info/RECORD
